feishu_bitable_query.py
main.py
feishu_bitable_query-0.4.dist-info/METADATA
feishu_bitable_query-0.4.dist-info/WHEEL
feishu_bitable_query-0.4.dist-info/top_level.txt
feishu_bitable_query-0.4.dist-info/RECORD
