Metadata-Version: 2.1
Name: feishu_bitable_query
Version: 0.4
Requires-Python: >=3.7
Requires-Dist: lark-oapi>=1.0.0
Requires-Dist: requests>=2.25.0
